brandpanel_api/__init__.py
brandpanel_api/api_client.py
brandpanel_api/configuration.py
brandpanel_api/rest.py
brandpanel_api/api/__init__.py
brandpanel_api/api/default_api.py
brandpanel_api/models/__init__.py
brandpanel_api/models/user.py
brandpanel_api/models/user_create.py
brandpanel_api/models/user_update.py
test/__init__.py
test/test_default_api.py
test/test_user.py
test/test_user_create.py
test/test_user_update.py
brandpanel_api-1.0.1.dist-info/METADATA
brandpanel_api-1.0.1.dist-info/WHEEL
brandpanel_api-1.0.1.dist-info/top_level.txt
brandpanel_api-1.0.1.dist-info/RECORD
