Metadata-Version: 2.1
Name: brandpanel-api
Version: 1.0.1
Summary: Dash Hudson - Insta
Home-page: UNKNOWN
Author: UNKNOWN
Author-email: tomek@dashhudson.com
License: UNKNOWN
Keywords: Swagger,Dash Hudson - Insta
Platform: UNKNOWN
Requires-Dist: certifi
Requires-Dist: python-dateutil
Requires-Dist: six (>=1.10)
Requires-Dist: urllib3 (>=1.15)
